miprobe/__init__.py
miprobe/mp_lib.py
miprobe-0.6.9.data/scripts/miprober
miprobe-0.6.9.dist-info/LICENSE
miprobe-0.6.9.dist-info/METADATA
miprobe-0.6.9.dist-info/WHEEL
miprobe-0.6.9.dist-info/top_level.txt
miprobe-0.6.9.dist-info/RECORD
