Metadata-Version: 2.1
Name: miprobe
Version: 0.6.9
Summary: MiProbe Sensor Serial Logging Tool.
Home-page: https://gitlab.com/evantaylor/miprobe
Author: Evan Taylor
Author-email: evan@evantaylor.pro
License: UNKNOWN
Keywords: miprobe,serial,sensors,biosensor,dynamodb,logger
Platform: UNKNOWN
Classifier: Development Status :: 3 - Alpha
Classifier: Intended Audience :: Science/Research
Classifier: Programming Language :: Python :: 3
Classifier: Operating System :: MacOS :: MacOS X
Classifier: Operating System :: POSIX :: Linux
Classifier: Operating System :: POSIX :: BSD :: FreeBSD
Classifier: License :: OSI Approved :: MIT License
Requires-Dist: urllib3
Requires-Dist: argparse
Requires-Dist: pyserial
Requires-Dist: pytz
Requires-Dist: tqdm
Requires-Dist: flask
Requires-Dist: simplejson
